{"date": "2026-06-07", "snapshots": [{"hour_utc": 10, "timestamp": "2026-06-07T10:16:16.673824+00:00", "games": [{"appid": 252490, "name": "Rust", "ccu": 131034, "twitch_viewers": 5947, "twitch_channels": 264, "viewers_by_lang": {"en": 3910, "de": 437, "fr": 298, "ru": 748, "es": 178, "ja": 340, "pl": 10, "uk": 5, "zh": 5, "it": 4, "pt": 8, "cs": 2, "tr": 1, "ar": 1}}, {"appid": 221100, "name": "DayZ", "ccu": 40487, "twitch_viewers": 3787, "twitch_channels": 181, "viewers_by_lang": {"en": 2810, "es": 162, "ru": 264, "de": 337, "fr": 67, "pl": 48, "sk": 27, "no": 25, "fi": 24, "bg": 6, "hu": 5, "uk": 4, "pt": 4, "it": 4}}, {"appid": 346110, "name": "ARK: Survival Evolved", "ccu": 25048, "twitch_viewers": 250, "twitch_channels": 47, "viewers_by_lang": {"zh": 93, "cs": 27, "de": 27, "en": 34, "ru": 21, "fr": 13, "ja": 12, "es": 19, "pt": 2, "bg": 2}}, {"appid": 2399830, "name": "ARK: Survival Ascended", "ccu": 30705, "twitch_viewers": 1778, "twitch_channels": 117, "viewers_by_lang": {"fr": 486, "ja": 571, "en": 364, "pt": 117, "de": 182, "es": 46, "ru": 11, "it": 1, "nl": 0}}, {"appid": 892970, "name": "Valheim", "ccu": 13776, "twitch_viewers": 289, "twitch_channels": 40, "viewers_by_lang": {"en": 162, "ru": 57, "hu": 20, "de": 28, "fr": 9, "pl": 3, "ja": 9, "es": 1}}, {"appid": 251570, "name": "7 Days to Die", "ccu": 23917, "twitch_viewers": 980, "twitch_channels": 84, "viewers_by_lang": {"en": 784, "ru": 35, "ja": 82, "fr": 16, "es": 11, "de": 41, "zh": 7, "th": 2, "pt": 1, "pl": 1, "cs": 0}}, {"appid": 1604030, "name": "V Rising", "ccu": 6022, "twitch_viewers": 208, "twitch_channels": 14, "viewers_by_lang": {"en": 200, "de": 3, "ru": 2, "sv": 1, "cs": 1, "tr": 1}}, {"appid": 440900, "name": "Conan Exiles", "ccu": 14719, "twitch_viewers": 673, "twitch_channels": 50, "viewers_by_lang": {"de": 349, "en": 227, "fr": 49, "ru": 18, "cs": 15, "pt": 9, "ja": 3, "es": 2, "ar": 1, "vi": 0}}, {"appid": 1172710, "name": "Dune: Awakening", "ccu": 7405, "twitch_viewers": 249, "twitch_channels": 35, "viewers_by_lang": {"en": 81, "de": 116, "fr": 31, "ru": 10, "pl": 3, "pt": 3, "cs": 2, "tr": 1, "es": 2}}, {"appid": 1623730, "name": "Palworld", "ccu": 34617, "twitch_viewers": 365, "twitch_channels": 46, "viewers_by_lang": {"fr": 128, "en": 135, "de": 31, "zh": 19, "ja": 30, "ru": 10, "es": 9, "pt": 3}}, {"appid": 108600, "name": "Project Zomboid", "ccu": 26732, "twitch_viewers": 334, "twitch_channels": 56, "viewers_by_lang": {"en": 162, "de": 53, "pt": 20, "fr": 46, "ru": 36, "zh": 5, "th": 3, "es": 9}}, {"appid": 1203620, "name": "Enshrouded", "ccu": 9905, "twitch_viewers": 299, "twitch_channels": 33, "viewers_by_lang": {"de": 209, "ru": 35, "fr": 24, "en": 23, "pl": 3, "zh": 4, "tr": 1}}, {"appid": 2646460, "name": "Soulmask", "ccu": 5186, "twitch_viewers": 35, "twitch_channels": 11, "viewers_by_lang": {"fr": 7, "zh": 9, "ru": 7, "de": 9, "en": 2, "ja": 1}}, {"appid": 2139460, "name": "Once Human", "ccu": 14596, "twitch_viewers": 797, "twitch_channels": 56, "viewers_by_lang": {"en": 455, "ru": 109, "ja": 83, "de": 82, "pt": 22, "zh": 19, "es": 14, "fr": 4, "uk": 4, "zh-hk": 2, "th": 2, "tl": 1, "ko": 0}}, {"appid": 1371580, "name": "Myth of Empires", "ccu": 857, "twitch_viewers": 0, "twitch_channels": 0, "viewers_by_lang": null}]}]}